{
  "users": {
    "704006042819756083": {
      "listeningTimeMs": 5633252,
      "serverPlaylistAdds": 1,
      "personalPlaylistAdds": 6,
      "songPlays": {
        "https://www.youtube.com/watch?v=7Eqy1u2frPU": {
          "title": "Bello FiGo - Mi Piace Venire (SWAG SBORRA) Amatur HD",
          "url": "https://www.youtube.com/watch?v=7Eqy1u2frPU",
          "thumbnail": "https://i.ytimg.com/vi/7Eqy1u2frPU/maxresdefault.jpg",
          "count": 6
        },
        "https://www.youtube.com/watch?v=hUgsVj6WwD4": {
          "title": "Lele Blade - SOUTHSIDE feat. Kid Yugi (Visual Video)",
          "url": "https://www.youtube.com/watch?v=hUgsVj6WwD4",
          "thumbnail": "https://i.ytimg.com/vi/hUgsVj6WwD4/hq720.jpg?sqp=-oaymwEcCOgCEMoBSFXyq4qpAw4IARUAAIhCGAFwAcABBg==&rs=AOn4CLCtZnqQmMEdaoyi5PGlCHYu-m9QQw",
          "count": 1
        },
        "https://www.youtube.com/watch?v=khi1VULb0uY": {
          "title": "KID YUGI - DRAGO BIANCO (VISUAL)",
          "url": "https://www.youtube.com/watch?v=khi1VULb0uY",
          "thumbnail": "https://i.ytimg.com/vi/khi1VULb0uY/hq720.jpg?sqp=-oaymwEcCOgCEMoBSFXyq4qpAw4IARUAAIhCGAFwAcABBg==&rs=AOn4CLC1r2wF2OVDSFzw3aRo-QwU8dsZqw",
          "count": 1
        },
        "https://www.youtube.com/watch?v=iehwpE942u8": {
          "title": "Writings on the Wall",
          "url": "https://www.youtube.com/watch?v=iehwpE942u8",
          "thumbnail": "https://i.ytimg.com/vi/iehwpE942u8/hq720.jpg?sqp=-oaymwEcCOgCEMoBSFXyq4qpAw4IARUAAIhCGAFwAcABBg==&rs=AOn4CLByGJ2yomR9tTX8WvgJ_fAWTr4uig",
          "count": 3
        },
        "https://www.youtube.com/watch?v=CmSRd6S9Gx4": {
          "title": "Too Many Nights",
          "url": "https://www.youtube.com/watch?v=CmSRd6S9Gx4",
          "thumbnail": "https://i.ytimg.com/vi/CmSRd6S9Gx4/hqdefault.jpg?sqp=-oaymwEbCKgBEF5IVfKriqkDDggBFQAAiEIYAXABwAEG&rs=AOn4CLC8dfZu_eJQSfnbbVlmGhuxWnckgQ",
          "count": 2
        },
        "https://www.youtube.com/watch?v=2RSsRfcU7Ac": {
          "title": "ANNA - ENERGY",
          "url": "https://www.youtube.com/watch?v=2RSsRfcU7Ac",
          "thumbnail": "https://i.ytimg.com/vi/2RSsRfcU7Ac/hq720.jpg?sqp=-oaymwEcCOgCEMoBSFXyq4qpAw4IARUAAIhCGAFwAcABBg==&rs=AOn4CLD510rZT1TLEC7aUmKqp1Bif4nhzw",
          "count": 2
        },
        "https://www.youtube.com/watch?v=4tj6hfn-Vb8": {
          "title": "Wasted",
          "url": "https://www.youtube.com/watch?v=4tj6hfn-Vb8",
          "thumbnail": "https://i.ytimg.com/vi/4tj6hfn-Vb8/maxresdefault.jpg",
          "count": 1
        },
        "https://www.youtube.com/watch?v=JdVlhIYYR8w": {
          "title": "Melons - Man Down!",
          "url": "https://www.youtube.com/watch?v=JdVlhIYYR8w",
          "thumbnail": "https://i.ytimg.com/vi_webp/JdVlhIYYR8w/maxresdefault.webp",
          "count": 4
        },
        "https://www.youtube.com/watch?v=MTdk6HeGszM": {
          "title": "Melons - Man Down 2!",
          "url": "https://www.youtube.com/watch?v=MTdk6HeGszM",
          "thumbnail": "https://i.ytimg.com/vi/MTdk6HeGszM/hq720.jpg?sqp=-oaymwEcCOgCEMoBSFXyq4qpAw4IARUAAIhCGAFwAcABBg==&rs=AOn4CLAlLpHTuB5vl_jR5FLLjayE8yTT_Q",
          "count": 1
        },
        "https://www.youtube.com/watch?v=9NMJ0m3jtqM": {
          "title": "Melons - Man Down 3! (prod. Ddusi) (Official Video)",
          "url": "https://www.youtube.com/watch?v=9NMJ0m3jtqM",
          "thumbnail": "https://i.ytimg.com/vi/9NMJ0m3jtqM/hq720.jpg?sqp=-oaymwEcCOgCEMoBSFXyq4qpAw4IARUAAIhCGAFwAcABBg==&rs=AOn4CLC8Y-6s4ECqCINo9JZn-pTeGJwQFQ",
          "count": 1
        },
        "https://www.youtube.com/watch?v=sEhy-RXkNo0": {
          "title": "Rihanna - Man Down",
          "url": "https://www.youtube.com/watch?v=sEhy-RXkNo0",
          "thumbnail": "https://i.ytimg.com/vi/sEhy-RXkNo0/hq720.jpg?sqp=-oaymwEcCOgCEMoBSFXyq4qpAw4IARUAAIhCGAFwAcABBg==&rs=AOn4CLCVjp3IzXOgmbxtq_QyMR0y4G5Ijg",
          "count": 1
        },
        "https://www.youtube.com/watch?v=B0MS736ZL00": {
          "title": "Melons, Ddusi - Man Down 4! (Official Video)",
          "url": "https://www.youtube.com/watch?v=B0MS736ZL00",
          "thumbnail": "https://i.ytimg.com/vi/B0MS736ZL00/maxresdefault.jpg",
          "count": 3
        },
        "https://www.youtube.com/watch?v=b-QCLrTN5pE": {
          "title": "With That (feat. Duke)",
          "url": "https://www.youtube.com/watch?v=b-QCLrTN5pE",
          "thumbnail": "https://i.ytimg.com/vi_webp/b-QCLrTN5pE/maxresdefault.webp",
          "count": 1
        }
      },
      "username": "caccaboss89",
      "global_name": "抜刀隊",
      "avatar": "602acfadc35915254bf45d2f2bdeaa48",
      "discriminator": "0"
    },
    "1373779309877006482": {
      "listeningTimeMs": 5633252,
      "serverPlaylistAdds": 2,
      "personalPlaylistAdds": 1,
      "songPlays": {
        "https://www.youtube.com/watch?v=7Eqy1u2frPU": {
          "title": "Bello FiGo - Mi Piace Venire (SWAG SBORRA) Amatur HD",
          "url": "https://www.youtube.com/watch?v=7Eqy1u2frPU",
          "thumbnail": "https://i.ytimg.com/vi/7Eqy1u2frPU/maxresdefault.jpg",
          "count": 6
        },
        "https://www.youtube.com/watch?v=hUgsVj6WwD4": {
          "title": "Lele Blade - SOUTHSIDE feat. Kid Yugi (Visual Video)",
          "url": "https://www.youtube.com/watch?v=hUgsVj6WwD4",
          "thumbnail": "https://i.ytimg.com/vi/hUgsVj6WwD4/hq720.jpg?sqp=-oaymwEcCOgCEMoBSFXyq4qpAw4IARUAAIhCGAFwAcABBg==&rs=AOn4CLCtZnqQmMEdaoyi5PGlCHYu-m9QQw",
          "count": 1
        },
        "https://www.youtube.com/watch?v=khi1VULb0uY": {
          "title": "KID YUGI - DRAGO BIANCO (VISUAL)",
          "url": "https://www.youtube.com/watch?v=khi1VULb0uY",
          "thumbnail": "https://i.ytimg.com/vi/khi1VULb0uY/hq720.jpg?sqp=-oaymwEcCOgCEMoBSFXyq4qpAw4IARUAAIhCGAFwAcABBg==&rs=AOn4CLC1r2wF2OVDSFzw3aRo-QwU8dsZqw",
          "count": 1
        },
        "https://www.youtube.com/watch?v=iehwpE942u8": {
          "title": "Writings on the Wall",
          "url": "https://www.youtube.com/watch?v=iehwpE942u8",
          "thumbnail": "https://i.ytimg.com/vi/iehwpE942u8/hq720.jpg?sqp=-oaymwEcCOgCEMoBSFXyq4qpAw4IARUAAIhCGAFwAcABBg==&rs=AOn4CLByGJ2yomR9tTX8WvgJ_fAWTr4uig",
          "count": 3
        },
        "https://www.youtube.com/watch?v=CmSRd6S9Gx4": {
          "title": "Too Many Nights",
          "url": "https://www.youtube.com/watch?v=CmSRd6S9Gx4",
          "thumbnail": "https://i.ytimg.com/vi/CmSRd6S9Gx4/hqdefault.jpg?sqp=-oaymwEbCKgBEF5IVfKriqkDDggBFQAAiEIYAXABwAEG&rs=AOn4CLC8dfZu_eJQSfnbbVlmGhuxWnckgQ",
          "count": 2
        },
        "https://www.youtube.com/watch?v=2RSsRfcU7Ac": {
          "title": "ANNA - ENERGY",
          "url": "https://www.youtube.com/watch?v=2RSsRfcU7Ac",
          "thumbnail": "https://i.ytimg.com/vi/2RSsRfcU7Ac/hq720.jpg?sqp=-oaymwEcCOgCEMoBSFXyq4qpAw4IARUAAIhCGAFwAcABBg==&rs=AOn4CLD510rZT1TLEC7aUmKqp1Bif4nhzw",
          "count": 2
        },
        "https://www.youtube.com/watch?v=4tj6hfn-Vb8": {
          "title": "Wasted",
          "url": "https://www.youtube.com/watch?v=4tj6hfn-Vb8",
          "thumbnail": "https://i.ytimg.com/vi/4tj6hfn-Vb8/maxresdefault.jpg",
          "count": 1
        },
        "https://www.youtube.com/watch?v=JdVlhIYYR8w": {
          "title": "Melons - Man Down!",
          "url": "https://www.youtube.com/watch?v=JdVlhIYYR8w",
          "thumbnail": "https://i.ytimg.com/vi_webp/JdVlhIYYR8w/maxresdefault.webp",
          "count": 4
        },
        "https://www.youtube.com/watch?v=MTdk6HeGszM": {
          "title": "Melons - Man Down 2!",
          "url": "https://www.youtube.com/watch?v=MTdk6HeGszM",
          "thumbnail": "https://i.ytimg.com/vi/MTdk6HeGszM/hq720.jpg?sqp=-oaymwEcCOgCEMoBSFXyq4qpAw4IARUAAIhCGAFwAcABBg==&rs=AOn4CLAlLpHTuB5vl_jR5FLLjayE8yTT_Q",
          "count": 1
        },
        "https://www.youtube.com/watch?v=9NMJ0m3jtqM": {
          "title": "Melons - Man Down 3! (prod. Ddusi) (Official Video)",
          "url": "https://www.youtube.com/watch?v=9NMJ0m3jtqM",
          "thumbnail": "https://i.ytimg.com/vi/9NMJ0m3jtqM/hq720.jpg?sqp=-oaymwEcCOgCEMoBSFXyq4qpAw4IARUAAIhCGAFwAcABBg==&rs=AOn4CLC8Y-6s4ECqCINo9JZn-pTeGJwQFQ",
          "count": 1
        },
        "https://www.youtube.com/watch?v=sEhy-RXkNo0": {
          "title": "Rihanna - Man Down",
          "url": "https://www.youtube.com/watch?v=sEhy-RXkNo0",
          "thumbnail": "https://i.ytimg.com/vi/sEhy-RXkNo0/hq720.jpg?sqp=-oaymwEcCOgCEMoBSFXyq4qpAw4IARUAAIhCGAFwAcABBg==&rs=AOn4CLCVjp3IzXOgmbxtq_QyMR0y4G5Ijg",
          "count": 1
        },
        "https://www.youtube.com/watch?v=B0MS736ZL00": {
          "title": "Melons, Ddusi - Man Down 4! (Official Video)",
          "url": "https://www.youtube.com/watch?v=B0MS736ZL00",
          "thumbnail": "https://i.ytimg.com/vi/B0MS736ZL00/maxresdefault.jpg",
          "count": 3
        },
        "https://www.youtube.com/watch?v=b-QCLrTN5pE": {
          "title": "With That (feat. Duke)",
          "url": "https://www.youtube.com/watch?v=b-QCLrTN5pE",
          "thumbnail": "https://i.ytimg.com/vi_webp/b-QCLrTN5pE/maxresdefault.webp",
          "count": 1
        }
      },
      "username": "lil_nga0542_15301",
      "global_name": "Lil_NGA",
      "avatar": null,
      "discriminator": "0"
    }
  },
  "global": {
    "songsStarted": 27,
    "songsCompleted": 16,
    "songPlays": {
      "https://www.youtube.com/watch?v=7Eqy1u2frPU": {
        "title": "Bello FiGo - Mi Piace Venire (SWAG SBORRA) Amatur HD",
        "url": "https://www.youtube.com/watch?v=7Eqy1u2frPU",
        "thumbnail": "https://i.ytimg.com/vi/7Eqy1u2frPU/maxresdefault.jpg",
        "count": 6
      },
      "https://www.youtube.com/watch?v=hUgsVj6WwD4": {
        "title": "Lele Blade - SOUTHSIDE feat. Kid Yugi (Visual Video)",
        "url": "https://www.youtube.com/watch?v=hUgsVj6WwD4",
        "thumbnail": "https://i.ytimg.com/vi/hUgsVj6WwD4/hq720.jpg?sqp=-oaymwEcCOgCEMoBSFXyq4qpAw4IARUAAIhCGAFwAcABBg==&rs=AOn4CLCtZnqQmMEdaoyi5PGlCHYu-m9QQw",
        "count": 1
      },
      "https://www.youtube.com/watch?v=khi1VULb0uY": {
        "title": "KID YUGI - DRAGO BIANCO (VISUAL)",
        "url": "https://www.youtube.com/watch?v=khi1VULb0uY",
        "thumbnail": "https://i.ytimg.com/vi/khi1VULb0uY/hq720.jpg?sqp=-oaymwEcCOgCEMoBSFXyq4qpAw4IARUAAIhCGAFwAcABBg==&rs=AOn4CLC1r2wF2OVDSFzw3aRo-QwU8dsZqw",
        "count": 1
      },
      "https://www.youtube.com/watch?v=iehwpE942u8": {
        "title": "Writings on the Wall",
        "url": "https://www.youtube.com/watch?v=iehwpE942u8",
        "thumbnail": "https://i.ytimg.com/vi/iehwpE942u8/hq720.jpg?sqp=-oaymwEcCOgCEMoBSFXyq4qpAw4IARUAAIhCGAFwAcABBg==&rs=AOn4CLByGJ2yomR9tTX8WvgJ_fAWTr4uig",
        "count": 3
      },
      "https://www.youtube.com/watch?v=CmSRd6S9Gx4": {
        "title": "Too Many Nights",
        "url": "https://www.youtube.com/watch?v=CmSRd6S9Gx4",
        "thumbnail": "https://i.ytimg.com/vi/CmSRd6S9Gx4/hqdefault.jpg?sqp=-oaymwEbCKgBEF5IVfKriqkDDggBFQAAiEIYAXABwAEG&rs=AOn4CLC8dfZu_eJQSfnbbVlmGhuxWnckgQ",
        "count": 2
      },
      "https://www.youtube.com/watch?v=2RSsRfcU7Ac": {
        "title": "ANNA - ENERGY",
        "url": "https://www.youtube.com/watch?v=2RSsRfcU7Ac",
        "thumbnail": "https://i.ytimg.com/vi/2RSsRfcU7Ac/hq720.jpg?sqp=-oaymwEcCOgCEMoBSFXyq4qpAw4IARUAAIhCGAFwAcABBg==&rs=AOn4CLD510rZT1TLEC7aUmKqp1Bif4nhzw",
        "count": 2
      },
      "https://www.youtube.com/watch?v=4tj6hfn-Vb8": {
        "title": "Wasted",
        "url": "https://www.youtube.com/watch?v=4tj6hfn-Vb8",
        "thumbnail": "https://i.ytimg.com/vi/4tj6hfn-Vb8/maxresdefault.jpg",
        "count": 1
      },
      "https://www.youtube.com/watch?v=JdVlhIYYR8w": {
        "title": "Melons - Man Down!",
        "url": "https://www.youtube.com/watch?v=JdVlhIYYR8w",
        "thumbnail": "https://i.ytimg.com/vi_webp/JdVlhIYYR8w/maxresdefault.webp",
        "count": 4
      },
      "https://www.youtube.com/watch?v=MTdk6HeGszM": {
        "title": "Melons - Man Down 2!",
        "url": "https://www.youtube.com/watch?v=MTdk6HeGszM",
        "thumbnail": "https://i.ytimg.com/vi/MTdk6HeGszM/hq720.jpg?sqp=-oaymwEcCOgCEMoBSFXyq4qpAw4IARUAAIhCGAFwAcABBg==&rs=AOn4CLAlLpHTuB5vl_jR5FLLjayE8yTT_Q",
        "count": 1
      },
      "https://www.youtube.com/watch?v=9NMJ0m3jtqM": {
        "title": "Melons - Man Down 3! (prod. Ddusi) (Official Video)",
        "url": "https://www.youtube.com/watch?v=9NMJ0m3jtqM",
        "thumbnail": "https://i.ytimg.com/vi/9NMJ0m3jtqM/hq720.jpg?sqp=-oaymwEcCOgCEMoBSFXyq4qpAw4IARUAAIhCGAFwAcABBg==&rs=AOn4CLC8Y-6s4ECqCINo9JZn-pTeGJwQFQ",
        "count": 1
      },
      "https://www.youtube.com/watch?v=sEhy-RXkNo0": {
        "title": "Rihanna - Man Down",
        "url": "https://www.youtube.com/watch?v=sEhy-RXkNo0",
        "thumbnail": "https://i.ytimg.com/vi/sEhy-RXkNo0/hq720.jpg?sqp=-oaymwEcCOgCEMoBSFXyq4qpAw4IARUAAIhCGAFwAcABBg==&rs=AOn4CLCVjp3IzXOgmbxtq_QyMR0y4G5Ijg",
        "count": 1
      },
      "https://www.youtube.com/watch?v=B0MS736ZL00": {
        "title": "Melons, Ddusi - Man Down 4! (Official Video)",
        "url": "https://www.youtube.com/watch?v=B0MS736ZL00",
        "thumbnail": "https://i.ytimg.com/vi/B0MS736ZL00/maxresdefault.jpg",
        "count": 3
      },
      "https://www.youtube.com/watch?v=b-QCLrTN5pE": {
        "title": "With That (feat. Duke)",
        "url": "https://www.youtube.com/watch?v=b-QCLrTN5pE",
        "thumbnail": "https://i.ytimg.com/vi_webp/b-QCLrTN5pE/maxresdefault.webp",
        "count": 1
      }
    }
  },
  "lastUpdated": "2026-07-01T03:06:57.287Z"
}