{
  "users": {
    "704006042819756083": {
      "listeningTimeMs": 41448577,
      "serverPlaylistAdds": 3,
      "personalPlaylistAdds": 0,
      "username": "caccaboss89",
      "global_name": "抜刀隊",
      "avatar": "602acfadc35915254bf45d2f2bdeaa48",
      "discriminator": "0"
    },
    "894275339495297024": {
      "listeningTimeMs": 3147900,
      "serverPlaylistAdds": 0,
      "personalPlaylistAdds": 0
    },
    "1439293517276119224": {
      "listeningTimeMs": 41210644,
      "serverPlaylistAdds": 40,
      "personalPlaylistAdds": 54,
      "username": "lorenzo_dsz08",
      "global_name": "Lorenzo419",
      "avatar": null,
      "discriminator": "0"
    },
    "1066462518903570503": {
      "listeningTimeMs": 13661299,
      "serverPlaylistAdds": 0,
      "personalPlaylistAdds": 0,
      "username": "tedescoduro",
      "global_name": "TEDESCODURO",
      "avatar": "7d055e5389315159d48942a3f94a6a40",
      "discriminator": "0"
    },
    "1373779309877006482": {
      "listeningTimeMs": 38656316,
      "serverPlaylistAdds": 0,
      "personalPlaylistAdds": 0,
      "username": "lil_nga0542_15301",
      "global_name": "Lil_NGA",
      "avatar": null,
      "discriminator": "0"
    },
    "717842969331367986": {
      "listeningTimeMs": 15783488,
      "serverPlaylistAdds": 0,
      "personalPlaylistAdds": 0,
      "username": "alex_the_real",
      "global_name": "Lil Alex",
      "avatar": "98f6b206d11cc9d759ab66494df3cd7c",
      "discriminator": "0"
    }
  },
  "global": {
    "songsStarted": 268,
    "songsCompleted": 288
  },
  "lastUpdated": "2026-03-15T23:45:11.633Z"
}